{
  "type": "FeatureCollection",
  "features": [
    {
      "type": "Feature",
      "properties": {},
      "geometry": {
        "coordinates": [
          [
            [
              35.048202846301876,
              33.10039728275548
            ],
            [
              35.15578489856293,
              33.09163427256888
            ],
            [
              35.15820291093533,
              33.085984793755
            ],
            [
              35.17673553504011,
              33.094824967413174
            ],
            [
              35.19408693548726,
              33.0864370626079
            ],
            [
              35.20659507939243,
              33.08962210532276
            ],
            [
              35.21071815675407,
              33.10084518514488
            ],
            [
              35.2272947296465,
              33.098089585242676
            ],
            [
              35.23609916886443,
              33.092220636384056
            ],
            [
              35.29160162624973,
              33.10878036851963
            ],
            [
              35.29859106612392,
              33.101495809883275
            ],
            [
              35.31596958224503,
              33.10439531681459
            ],
            [
              35.32506381070928,
              33.09594004364999
            ],
            [
              35.32068734850202,
              33.087871281332326
            ],
            [
              35.33425069257669,
              33.07676536142718
            ],
            [
              35.34730658275021,
              33.0604655466898
            ],
            [
              35.37809992627416,
              33.05509875749644
            ],
            [
              35.38147490877839,
              33.06234962648409
            ],
            [
              35.43048264832285,
              33.06634658168957
            ],
            [
              35.445102993661806,
              33.09107252849218
            ],
            [
              35.50306331088703,
              33.093476965431805
            ],
            [
              35.50289285309407,
              33.11724721385468
            ],
            [
              35.52031782171659,
              33.116772525279
            ],
            [
              35.53274482233107,
              33.134512479214465
            ],
            [
              35.526597434653354,
              33.13938938991504
            ],
            [
              35.54055024151944,
              33.20067284761315
            ],
            [
              35.53571490777421,
              33.20891917124905
            ],
            [
              35.539058256797745,
              33.22785717243188
            ],
            [
              35.545768793623324,
              33.23735625149686
            ],
            [
              35.545155812472444,
              33.25334941889653
            ],
            [
              35.55611484162844,
              33.25881920031421
            ],
            [
              35.55709470054262,
              33.2645377068918
            ],
            [
              35.564912974213115,
              33.27474882452533
            ],
            [
              35.56197546809341,
              33.284360521697096
            ],
            [
              35.56859448056605,
              33.29196415400075
            ],
            [
              35.58431107344376,
              33.282765740283594
            ],
            [
              35.58490711580211,
              33.2675793255797
            ],
            [
              35.62471865336934,
              33.24155453065271
            ],
            [
              35.620629074250076,
              33.27088465658443
            ],
            [
              35.643611452982014,
              33.280602341544665
            ],
            [
              35.659054621365755,
              33.27437705889446
            ],
            [
              35.67505101578098,
              33.29401291037951
            ],
            [
              35.71433623737457,
              33.311302128200495
            ],
            [
              35.71195808618455,
              33.32480811210951
            ],
            [
              35.728636289744145,
              33.33104675776349
            ],
            [
              35.737671289302966,
              33.32055650291892
            ],
            [
              35.79297563400621,
              33.34051564104715
            ],
            [
              35.7774115291875,
              33.387736690094485
            ],
            [
              35.61736297953988,
              33.32820505256453
            ],
            [
              35.50987897952945,
              33.34130611182964
            ],
            [
              35.46422376493223,
              33.139507134598844
            ],
            [
              35.382597774493576,
              33.11733800993423
            ],
            [
              35.32728644605828,
              33.15851665438166
            ],
            [
              35.173718199894154,
              33.14010736790742
            ],
            [
              35.06635658763096,
              33.14648969163788
            ],
            [
              35.048202846301876,
              33.10039728275548
            ]
          ]
        ],
        "type": "Polygon"
      }
    }
  ]
}